{
  "id": "634a34e6116f4397bee478374708de9b",
  "price": {
    "totalPaymentPrice": {
      "paymentCurrencyAmount": 23180,
      "paymentCurrencyCode": "UAH",
      "paymentCurrencyExchangeRate": 1,
      "paymentCurrencySymbol": "₴"
    },
    "totalPrice": {
      "basePayoutCurrencyCode": "USD",
      "basePayoutPrice": 820,
      "convenienceFee": 0,
      "currencyCode": "UAH",
      "discount": 37820,
      "discountPrice": 23180,
      "originalPrice": 61000,
      "originalUnitPrice": null,
      "unitPrice": null,
      "vat": 0,
      "voucherDiscount": 0
    }
  }
}